tokenx/__init__.py
tokenx/constants.py
tokenx/cost_calc.py
tokenx/errors.py
tokenx/metrics.py
tokenx/model_prices.yaml
tokenx/yaml_loader.py
tokenx/providers/__init__.py
tokenx/providers/anthropic.py
tokenx/providers/base.py
tokenx/providers/openai.py
tokenx_core-0.2.9.dist-info/licenses/LICENSE
tokenx_core-0.2.9.dist-info/METADATA
tokenx_core-0.2.9.dist-info/WHEEL
tokenx_core-0.2.9.dist-info/top_level.txt
tokenx_core-0.2.9.dist-info/RECORD
