Metadata-Version: 2.4
Name: tokenx-core
Version: 0.2.9
Summary: Cross-provider LLM token tracking and cost calculation
Author-email: Deval Shah <deval@neurink.ai>
License: MIT License
Project-URL: Homepage, https://github.com/dvlshah/tokenx
Project-URL: Documentation, https://github.com/dvlshah/tokenx#readme
Project-URL: Repository, https://github.com/dvlshah/tokenx
Project-URL: Bug Tracker, https://github.com/dvlshah/tokenx/issues
Project-URL: Changelog, https://github.com/dvlshah/tokenx/blob/main/docs/CHANGELOG.md
Keywords: openai,pricing,observability,llm,anthropic,gemini
Classifier: Development Status :: 4 - Beta
Classifier: Intended Audience :: Developers
Classifier: License :: OSI Approved :: MIT License
Classifier: Operating System :: OS Independent
Classifier: Programming Language :: Python :: 3
Classifier: Programming Language :: Python :: 3.9
Classifier: Programming Language :: Python :: 3.10
Classifier: Programming Language :: Python :: 3.11
Classifier: Programming Language :: Python :: 3.12
Classifier: Topic :: Software Development :: Libraries :: Python Modules
Classifier: Topic :: Utilities
Classifier: Typing :: Typed
Requires-Python: >=3.9
License-File: LICENSE
Requires-Dist: tiktoken
Requires-Dist: pyyaml
Provides-Extra: dev
Requires-Dist: pytest; extra == "dev"
Requires-Dist: pytest-cov; extra == "dev"
Requires-Dist: pytest-mock; extra == "dev"
Requires-Dist: pytest-asyncio; extra == "dev"
Requires-Dist: ruff; extra == "dev"
Requires-Dist: pre-commit; extra == "dev"
Provides-Extra: openai
Requires-Dist: openai>=1.0.0; extra == "openai"
Provides-Extra: anthropic
Requires-Dist: anthropic>=0.18.0; extra == "anthropic"
Provides-Extra: gemini
Requires-Dist: google-generativeai>=0.3.0; extra == "gemini"
Provides-Extra: all
Requires-Dist: openai>=1.0.0; extra == "all"
Requires-Dist: anthropic>=0.18.0; extra == "all"
Requires-Dist: google-generativeai>=0.3.0; extra == "all"
Dynamic: license-file
